pyaudioreader/__init__.py
pyaudioreader/audiofile.py
pyaudioreader/microphone.py
pyaudioreader-0.0.1.dist-info/LICENSE
pyaudioreader-0.0.1.dist-info/METADATA
pyaudioreader-0.0.1.dist-info/WHEEL
pyaudioreader-0.0.1.dist-info/top_level.txt
pyaudioreader-0.0.1.dist-info/RECORD
